threezaconventions/__init__.py
threezaconventions/crypto.py
threezaconventions-0.0.3.dist-info/METADATA
threezaconventions-0.0.3.dist-info/WHEEL
threezaconventions-0.0.3.dist-info/entry_points.txt
threezaconventions-0.0.3.dist-info/top_level.txt
threezaconventions-0.0.3.dist-info/RECORD
