Metadata-Version: 2.1
Name: threezaconventions
Version: 0.0.3
Summary: Minimalist conventions used at www.3za.org 
Home-page: https://github.com/microprediction/threezaconventions
Author: microprediction
Author-email: info@3za.org
License: MIT
Platform: UNKNOWN
Classifier: License :: OSI Approved :: MIT License
Classifier: Programming Language :: Python :: 3
Classifier: Programming Language :: Python :: 3.7
Requires-Dist: pathlib
